onelibs
