Metadata-Version: 1.0
Name: onelibs
Version: 0.0.2
Summary: onelibs is an out-of-the-box libs written in python
Home-page: https://github.com/istommao/onelibs-python
Author: codingcat
Author-email: istommao@gmail.com
License: UNKNOWN
Keywords: onelibs
Platform: UNKNOWN
